AUTHORS.rst
CONTRIBUTING.rst
HISTORY.rst
MANIFEST.in
README.rst
setup.cfg
setup.py
docs/Makefile
docs/authors.rst
docs/conf.py
docs/contributing.rst
docs/history.rst
docs/index.rst
docs/installation.rst
docs/make.bat
docs/readme.rst
docs/usage.rst
osm_find_first/__init__.py
osm_find_first/_version.py
osm_find_first.egg-info/PKG-INFO
osm_find_first.egg-info/SOURCES.txt
osm_find_first.egg-info/dependency_links.txt
osm_find_first.egg-info/not-zip-safe
osm_find_first.egg-info/requires.txt
osm_find_first.egg-info/top_level.txt
tests/__init__.py
tests/test_osm_find_first.py