Metadata-Version: 1.1
Name: osm-find-first
Version: 0.3.0
Summary: Find the first version, incl. datetime, of objects in the OSM database
Home-page: https://github.com/rory/osm-find-first
Author: Rory McCann
Author-email: rory@technomancy.org
License: GPLv3+
Keywords: osm-find-first
Platform: UNKNOWN
Classifier: Development Status :: 2 - Pre-Alpha
Classifier: Intended Audience :: Developers
Classifier: License :: OSI Approved :: GNU General Public License v3 or later (GPLv3+)
Classifier: Natural Language :: English
Classifier: Programming Language :: Python :: 2
Classifier: Programming Language :: Python :: 2.7
Classifier: Programming Language :: Python :: 3
Classifier: Programming Language :: Python :: 3.3
Classifier: Programming Language :: Python :: 3.4
